TLC_main.v
// Main Module for Traffic Light Controller, follows schematic from paper
module TLC_main(
    input clk,
    input reset,
    input sensor1,
    input sensor2,
    input peak,
    output reg[1:0]  TL1,
    output reg[1:0]  TL2,
    output reg[1:0]  TL3,
    output reg[1:0]  TL4,
    output reg[1:0]  TL5,
    output reg[1:0]  TL6); 

    reg f16,f24,f35,f36,f25;

    // Do peak off-peak inputs from separate file
    
    
    integer Timer;

    initial begin
	 
        // Set Timer and flags to 0
        Timer <= 0;         
        Timer <= 0;
        TL1 <= 0;         TL2 <= 2;         TL3 <= 2;        TL4 <= 2;        TL5 <= 2;   
        TL6 <= 0;         f16 <= 0;         f24 <= 0;        f35 <= 0;  		f36 <= 0;
        f25 <= 0;  
    end	 
	 
	 // Reset conditions below , Initializes to TL1, TL6 green.
	 
    always @(posedge clk) 
        if (reset == 0) begin
            //initialize lights and flags
            Timer <= 0;
            TL1 <= 0;         TL2 <= 2;         TL3 <= 2;        TL4 <= 2;        TL5 <= 2;   
            TL6 <= 0;         f16 <= 0;         f24 <= 0;        f35 <= 0;  		f36 <= 0;
    		f25 <= 0;    
        end

    // Increment timer with each positive clock cycle transition
	always @(posedge clk)
        Timer <= Timer + 1;

		  
		  
    // Control Traffic light output based on Timer values
    always @(*) begin
	 
    // Peak condition cases
        if (peak) begin
            // Peak conditions
            case(TL1)
                0:if (Timer == 32) begin
                    Timer <= 0;
                    TL1 <= 1;
                end
                1:if ((Timer == 4) && (f16 == 0)) begin
                    Timer <= 0;
                    TL1 <= 2;
                    f16 <= 1; // set flag for next case execution
                end 
                2:if ((Timer == 4) && (f16 == 1)) begin
                    Timer <= 0;
                    TL2 <= 0;
                    f16 <= 0;  //reset flag and now tl goes high(2)
                end 
            endcase
            case(TL2)
                0:if (Timer == 32) begin
                    Timer <= 0;
                    TL2 <= 1;
                end
                1:if ((Timer == 4) && (f24 == 0)) begin
                    Timer <= 0;
                    TL2 <= 2;
                    f24 <= 1;
                end 
                2:if ((Timer == 4) && (f24 == 1)) begin
                    Timer <= 0;
                    TL3 <= 0;
                    f24 <= 0;
                end 
            endcase
            case(TL3)
                0:if (Timer == 16) begin
                    Timer <= 0;
                    TL3 <= 1;
                end
                1:if ((Timer == 4) && (f35 == 0)) begin
                    Timer <= 0;
                    TL3 <= 2;
                    f35 <= 1;
                end 
                2:if ((Timer == 4) && (f35 == 1)) begin
                    Timer <= 0;
                    TL1 <= 0;
                    f35 <= 0;
                end 
            endcase
            TL6 <= TL1; 
            TL4 <= TL2;
            TL5 <= TL3;
        end
    // Off-Peak condition cases
        
		else begin
		  
            // when both sensors are activated
            if ((sensor1 == 1) && (sensor2 == 1)) begin
                TL1 <= TL6; 
                TL2 <= TL4;
                TL3 <= TL5;
                case(TL1)
                    0:if (Timer == 16) begin
                        Timer <= 0;
                        TL1 <= 1;
                    end
                    1:if ((Timer == 4) && (f16 == 0)) begin
                        Timer <= 0;
                        TL1 <= 2;
                        f16 <= 1;
                    end 
                    2:if ((Timer == 4) && (f16 == 1)) begin
                        Timer <= 0;
                        TL2 <= 0;
                        f16 <= 0;
                    end 
                endcase
                case(TL2)
                    0:if (Timer == 16) begin
                        Timer <= 0;
                        TL2 <= 1;
                    end
                    1:if ((Timer == 4) && (f24 == 0)) begin
                        Timer <= 0;
                        TL2 <= 2;
                        f24 <= 1;
                    end 
                    2:if ((Timer == 4) && (f24 == 1)) begin
                        Timer <= 0;
                        TL3 <= 0;
                        f24<= 0;
                    end 
                endcase
                case(TL3)
                    0:if (Timer == 8) begin
                        Timer <= 0;
                        TL3 <= 1;
                    end
                    1:if ((Timer == 4) && (f35 == 0)) begin
                        Timer <= 0;
                        TL3 <= 2;
                        f35 <= 1;
                    end 
                    2:if ((Timer == 4) && (f35 == 1)) begin
                        Timer <= 0;
                        TL1 <= 0;
                        f35 <= 0;
                    end 
                endcase
            end
        	// when only sensor1 is activated
			else if ((sensor1 == 1) && (sensor2 == 0))begin 
                TL4 <= TL2;
                case(TL1)
                    0:if (Timer == 16) begin
                        Timer <= 0;
                        TL1 <= 1;
                        TL6 <= TL1;
                    end
                    1:if ((Timer == 4) && (f16 == 0)) begin
                        Timer <= 0;
                        TL1 <= 2;
                        TL6 <= TL1;
                        f16 <= 1;
                    end 
                    2:if ((Timer == 4) && (f16 == 1)) begin
                        Timer <= 0;
                        TL2 <= 0;
                        f16 <= 0;
                    end 
                endcase
                case(TL2)
                    0:if (Timer == 16) begin
                        Timer <= 0;
                        TL2 <= 1;
                    end
                    1:if ((Timer == 4) && (f24 == 0)) begin
                        Timer <= 0;
                        TL2 <= 2;
                        f24 <= 1;
                    end 
                    2:if ((Timer == 4) && (f24 == 1)) begin
                        Timer <= 0;
                        TL3 <= 0;
                        f24 <= 0;
								TL6 <= 0;
                    end 
                endcase
                case(TL3)
                    0:if (Timer == 8) begin
                        Timer <= 0;
                        TL3 <= 1;
                        TL6 <= TL3;
                    end
                    1:if ((Timer == 4) && (f36 == 0)) begin
                        Timer <= 0;
                        TL3 <= 2;
                        TL6 <= TL3;
								f36 <= 1;
                    end 
                    2:if ((Timer == 4) && (f36 == 1)) begin
                        Timer <= 0;
                        TL1 <= 0;
                        TL6 <= TL3;
								f36 <= 0;
                    end 
                endcase
            end
            // when sensor2 is only activated 
            else if ((sensor1 == 0) && (sensor1 == 1)) begin 
                TL6 <= TL1;
                case(TL1)
                    0:if (Timer == 16) begin
                        Timer <= 0;
                        TL1 <= 1;
                    end
                    1:if ((Timer == 4) && (f16 == 0))begin
                        Timer <= 0;
                        TL1 <= 2;
								f16 <= 1;
                    end 
                    2:if ((Timer == 4) && (f16 == 1)) begin
                        Timer <= 0;
                        TL4 <= 0;
								f16 <= 0;
                    end 
                endcase
                case(TL4)
                    0:if (Timer == 16) begin
                        Timer <= 0;
                        TL4 = 1;
                        TL2 <= TL4;
                    end
                    1:if ((Timer == 4) && (f24 == 0)) begin
                        Timer <= 0;
                        TL4 = 2;
                        TL2 <= TL4;
								f24 <= 1;
                    end 
                    2:if ((Timer == 4) && (f24 == 1)) begin
                        Timer <= 0;
                        TL5 <= 0;
								f24 <= 0;
                    end 
                endcase
                case(TL5)
                    0:if (Timer == 8) begin
                        Timer <= 0;
                        TL5 = 1;
                        TL2 <= TL5;
                    end
                    1:if ((Timer == 4) && (f25 == 0)) begin
                        Timer <= 0;
                        TL5 <= 2;
                        TL2 <= TL5;
								f25 <= 1;
                    end 
                    2:if ((Timer == 4) && (f25 == 1)) begin
                        Timer <= 0;
                        TL5 <= 0;
                        TL2 <= TL5;
								f25 <=0;
                    end 
                endcase
            end
            // when all sensors are deactivated
            else begin
                TL1 <= TL6; 
                TL2 <= TL4;
                case(TL1)
                    0:if (Timer == 16) begin
                        Timer <= 0;
                        TL1 <= 1;
                    end
                    1:if ((Timer == 4) && (f16 == 0)) begin
                        Timer <= 0;
                        TL1 <= 2;
						f16 <= 1;
                    end 
                    2:if ((Timer == 4) && (f16 == 1)) begin
                        Timer <= 0;
                        TL2 <= 0;
						f16 <= 0;
                    end 
                endcase
                case(TL2)
                    0:if (Timer == 16) begin
                        Timer <= 0;
                        TL2 <= 1;
                    end
                    1:if ((Timer == 4) && (f24 == 0)) begin
                        Timer <= 0;
                        TL2 <= 2;
						f24 <= 1;
                    end 
                    2:if ((Timer == 4) && (f24 == 1)) begin
                        Timer <= 0;
                        TL1 <= 0;
						f24 <= 0;
                    end 
                endcase                
            end
        end            
    end
endmodule

peak_offpeak.v
module peak_offpeak(
    input [7:0] hours,
    input pm,
    output reg peak);

// Peak Hour Periods -- 0700 – 0900, 1200 – 1400 and 1700 – 1900 hours
// Edit on Parth's PC
initial 
    peak = 0;

always @(*) begin
    if (~pm) begin
        if  ((hours[3:0] <= 9) && (hours[3:0] >= 7)) 
            peak <= 1;
        
        else 
            peak <= 0;
    end
    else begin
        if  (((hours[3:0] <= 2) && (hours[3:0] >= 0)) || ((hours[3:0] <= 7) && (hours[3:0] >= 5))) 
            peak <= 1;  
        else 
            peak <= 0;    
        end
    end

endmodule

12HourBCDclock.v
module TwelveHourBCDclock(
    input clk,
    input reset,
    input ena,
    output reg pm,
    output reg [7:0] hh,
    output reg [7:0] mm,
    output reg [7:0] ss); 
    
    // Starting from 1 am
    initial begin
        hh = 8'b00000001;
        ss = 8'b00000000;
        mm = 8'b00000000;
        pm = 1'b1;
    end
        
    
    // Logic changes at positive edge of clock, reset synchronous active low
    always @(posedge clk) begin

        // Count of register for Seconds increases at ena == 1, BCD encoding is done
        if (ena) begin 
            if (ss[3:0] < 9) 
                ss[3:0] <= ss[3:0] + 1;
            else begin
                ss[3:0] <= 0; 
                ss[7:4] <= ss[7:4] + 1;
            end

        // Increase in minute count and seconds rollover
        if(ss[7:4] == 5 && ss[3:0] == 9) begin 
            ss <= 0;
            if (mm[3:0] < 9) 
                mm[3:0] <= mm[3:0] + 1;
            else begin
                mm[3:0] <= 0; 
                mm[7:4] <= mm[7:4] + 1;
            end
        end

        // Increase in hours count and minutes rollover
        if(ss[7:4] == 5 && ss[3:0] == 9 && mm[7:4] == 5 && mm[3:0] == 9) begin 
            mm <= 0;
            if (hh[3:0] < 9) 
                hh[3:0] <= hh[3:0] + 1;
            else begin
                hh[3:0] <= 0; 
                hh[7:4] <= hh[7:4] + 1;
            end
        end

        // Rollover in hours from 12 pm/am to 1 am/pm
        if(ss[7:4] == 5 && ss[3:0] == 9 && mm[7:4] == 5 && mm[3:0] == 9 && hh[7:4] == 1 && hh[3:0] == 2) begin 
            hh <= 1;
        end

        // Complement pm at 11:59:59 am/pm to 12:00:00 pm/am
        if(ss[7:4] == 5 && ss[3:0] == 9 && mm[7:4] == 5 && mm[3:0] == 9 && hh[7:4] == 1 && hh[3:0] == 1) begin 
            pm <= ~pm;
        end

        end

        // Logic to reset the clock
        if(~reset) begin
            ss <= 0;
            hh[7:4] <= 0;
            hh[3:0] <= 1;
            pm <= 1;
            mm <= 0;
        end
    end
    
    

endmodule

Top_Module.v
module TLC_topModule(
    input clk,
    input reset,
    input ena,
    input sensor1,
    input sensor2,
    output [1:0] TL1,
    output [1:0] TL2,
    output [1:0] TL3,
    output [1:0] TL4,
    output [1:0] TL5,
    output [1:0] TL6,
    output peak,
    output pm,
    output [7:0] hh,
    output [7:0] mm,
    output [7:0] ss
);

TwelveHourBCDclock BCD_clk(
    .clk(clk),
    .ena(ena),
    .reset(reset),
    .hh(hh),
    .mm(mm),
    .ss(ss),
    .pm(pm)
);

peak_offpeak BCD_peak(
    .hours(hh),
    .pm(pm),
    .peak(peak)
);

TLC_main Tlc_1(
    .clk(clk),
    .reset(reset),
    .sensor1(sensor1),
    .sensor2(sensor2),
    .TL1(TL1),
    .TL2(TL2),
    .TL3(TL3),
    .TL4(TL4),
    .TL5(TL5),
    .TL6(TL6),
    .peak(peak)
);

endmodule

TLC_test.v
`timescale 1ns / 1ns


module TLC_tb;

    reg clk; reg reset;                                 // clk and reset
    reg ena; reg sensor1; reg sensor2;                  // enable and sensors

    wire [1:0] TL1; wire [1:0] TL2;                     // TL1 and TL2
    wire [1:0] TL3; wire [1:0] TL4;                     // TL3 and TL4
    wire [1:0] TL5; wire [1:0] TL6;                     // TL5 and TL6
    wire peak; wire pm;                                 // peak and pm
    wire [7:0] hh; wire [7:0] mm; wire [7:0] ss;        // hh, mm, ss

TLC_topModule dut0 (
    .clk(clk), .reset(reset), .ena(ena), .sensor1(sensor1), .sensor2(sensor2),
    .TL1(TL1), .TL2(TL2), .TL3(TL3), .TL4(TL4), .TL5(TL5), .TL6(TL6),
    .peak(peak), .pm(pm), .hh(hh), .mm(mm), .ss(ss)
);

// generate the clock

 initial begin

   clk = 1'b0;
   sensor1 = 0; sensor2 = 0;
   forever #1 clk = ~clk;
   forever #1000 sensor1 = ~sensor1;
   forever #500 sensor2 = ~sensor2;
 end

 initial begin
   $dumpvars();

    reset = 0; ena = 1; 

    #10 reset = 1; 

    #500 $finish;
 end

endmodule

dump.vcd
$date
	Wed Mar 23 19:46:27 2022
$end
$version
	Icarus Verilog
$end
$timescale
	1ns
$end
$scope module TLC_tb $end
$var wire 8 ! ss [7:0] $end
$var wire 1 " pm $end
$var wire 1 # peak $end
$var wire 8 $ mm [7:0] $end
$var wire 8 % hh [7:0] $end
$var wire 2 & TL6 [1:0] $end
$var wire 2 ' TL5 [1:0] $end
$var wire 2 ( TL4 [1:0] $end
$var wire 2 ) TL3 [1:0] $end
$var wire 2 * TL2 [1:0] $end
$var wire 2 + TL1 [1:0] $end
$var reg 1 , clk $end
$var reg 1 - ena $end
$var reg 1 . reset $end
$var reg 1 / sensor1 $end
$var reg 1 0 sensor2 $end
$scope module dut0 $end
$var wire 1 , clk $end
$var wire 1 - ena $end
$var wire 1 . reset $end
$var wire 1 / sensor1 $end
$var wire 1 0 sensor2 $end
$var wire 8 1 ss [7:0] $end
$var wire 1 " pm $end
$var wire 1 # peak $end
$var wire 8 2 mm [7:0] $end
$var wire 8 3 hh [7:0] $end
$var wire 2 4 TL6 [1:0] $end
$var wire 2 5 TL5 [1:0] $end
$var wire 2 6 TL4 [1:0] $end
$var wire 2 7 TL3 [1:0] $end
$var wire 2 8 TL2 [1:0] $end
$var wire 2 9 TL1 [1:0] $end
$scope module BCD_clk $end
$var wire 1 , clk $end
$var wire 1 - ena $end
$var wire 1 . reset $end
$var reg 8 : hh [7:0] $end
$var reg 8 ; mm [7:0] $end
$var reg 1 " pm $end
$var reg 8 < ss [7:0] $end
$upscope $end
$scope module BCD_peak $end
$var wire 8 = hours [7:0] $end
$var wire 1 " pm $end
$var reg 1 # peak $end
$upscope $end
$scope module Tlc_1 $end
$var wire 1 , clk $end
$var wire 1 # peak $end
$var wire 1 . reset $end
$var wire 1 / sensor1 $end
$var wire 1 0 sensor2 $end
$var reg 2 > TL1 [1:0] $end
$var reg 2 ? TL2 [1:0] $end
$var reg 2 @ TL3 [1:0] $end
$var reg 2 A TL4 [1:0] $end
$var reg 2 B TL5 [1:0] $end
$var reg 2 C TL6 [1:0] $end
$var reg 1 D f16 $end
$var reg 1 E f24 $end
$var reg 1 F f25 $end
$var reg 1 G f35 $end
$var reg 1 H f36 $end
$var integer 32 I Timer [31:0] $end
$upscope $end
$upscope $end
$upscope $end
$enddefinitions $end
#0
$dumpvars
b0 I
0H
0G
0F
0E
0D
bx C
b10 B
bx A
b10 @
bx ?
bx >
b1 =
b0 <
b0 ;
b1 :
bx 9
bx 8
b10 7
bx 6
b10 5
bx 4
b1 3
b0 2
b0 1
00
0/
0.
1-
0,
bx +
bx *
b10 )
bx (
b10 '
bx &
b1 %
b0 $
1#
1"
b0 !
$end
#1
b0 !
b0 1
b0 <
b0 &
b0 4
b0 C
b10 (
b10 6
b10 A
b10 *
b10 8
b10 ?
b0 +
b0 9
b0 >
b0 I
1,
#2
0,
#3
b1 I
b0 !
b0 1
b0 <
1,
#4
0,
#5
b0 !
b0 1
b0 <
b0 I
1,
#6
0,
#7
b1 I
b0 !
b0 1
b0 <
1,
#8
0,
#9
b0 !
b0 1
b0 <
b0 I
1,
#10
0,
1.
#11
b1 I
b1 !
b1 1
b1 <
1,
#12
0,
#13
b10 !
b10 1
b10 <
b10 I
1,
#14
0,
#15
b11 I
b11 !
b11 1
b11 <
1,
#16
0,
#17
b100 !
b100 1
b100 <
b100 I
1,
#18
0,
#19
b101 I
b101 !
b101 1
b101 <
1,
#20
0,
#21
b110 !
b110 1
b110 <
b110 I
1,
#22
0,
#23
b111 I
b111 !
b111 1
b111 <
1,
#24
0,
#25
b1000 !
b1000 1
b1000 <
b1000 I
1,
#26
0,
#27
b1001 I
b1001 !
b1001 1
b1001 <
1,
#28
0,
#29
b10000 !
b10000 1
b10000 <
b1010 I
1,
#30
0,
#31
b1011 I
b10001 !
b10001 1
b10001 <
1,
#32
0,
#33
b10010 !
b10010 1
b10010 <
b1100 I
1,
#34
0,
#35
b1101 I
b10011 !
b10011 1
b10011 <
1,
#36
0,
#37
b10100 !
b10100 1
b10100 <
b1110 I
1,
#38
0,
#39
b1111 I
b10101 !
b10101 1
b10101 <
1,
#40
0,
#41
b10110 !
b10110 1
b10110 <
b10000 I
1,
#42
0,
#43
b10001 I
b10111 !
b10111 1
b10111 <
1,
#44
0,
#45
b11000 !
b11000 1
b11000 <
b10010 I
1,
#46
0,
#47
b10011 I
b11001 !
b11001 1
b11001 <
1,
#48
0,
#49
b100000 !
b100000 1
b100000 <
b10100 I
1,
#50
0,
#51
b10101 I
b100001 !
b100001 1
b100001 <
1,
#52
0,
#53
b100010 !
b100010 1
b100010 <
b10110 I
1,
#54
0,
#55
b10111 I
b100011 !
b100011 1
b100011 <
1,
#56
0,
#57
b100100 !
b100100 1
b100100 <
b11000 I
1,
#58
0,
#59
b11001 I
b100101 !
b100101 1
b100101 <
1,
#60
0,
#61
b100110 !
b100110 1
b100110 <
b11010 I
1,
#62
0,
#63
b11011 I
b100111 !
b100111 1
b100111 <
1,
#64
0,
#65
b101000 !
b101000 1
b101000 <
b11100 I
1,
#66
0,
#67
b11101 I
b101001 !
b101001 1
b101001 <
1,
#68
0,
#69
b110000 !
b110000 1
b110000 <
b11110 I
1,
#70
0,
#71
b11111 I
b110001 !
b110001 1
b110001 <
1,
#72
0,
#73
b1 &
b1 4
b1 C
b1 +
b1 9
b1 >
b110010 !
b110010 1
b110010 <
b0 I
1,
#74
0,
#75
b1 I
b110011 !
b110011 1
b110011 <
1,
#76
0,
#77
b110100 !
b110100 1
b110100 <
b10 I
1,
#78
0,
#79
b11 I
b110101 !
b110101 1
b110101 <
1,
#80
0,
#81
b10 &
b10 4
b10 C
1D
b10 +
b10 9
b10 >
b110110 !
b110110 1
b110110 <
b0 I
1,
#82
0,
#83
b1 I
b110111 !
b110111 1
b110111 <
1,
#84
0,
#85
b111000 !
b111000 1
b111000 <
b10 I
1,
#86
0,
#87
b11 I
b111001 !
b111001 1
b111001 <
1,
#88
0,
#89
b0 (
b0 6
b0 A
0D
b0 *
b0 8
b0 ?
b1000000 !
b1000000 1
b1000000 <
b0 I
1,
#90
0,
#91
b1 I
b1000001 !
b1000001 1
b1000001 <
1,
#92
0,
#93
b1000010 !
b1000010 1
b1000010 <
b10 I
1,
#94
0,
#95
b11 I
b1000011 !
b1000011 1
b1000011 <
1,
#96
0,
#97
b1000100 !
b1000100 1
b1000100 <
b100 I
1,
#98
0,
#99
b101 I
b1000101 !
b1000101 1
b1000101 <
1,
#100
0,
#101
b1000110 !
b1000110 1
b1000110 <
b110 I
1,
#102
0,
#103
b111 I
b1000111 !
b1000111 1
b1000111 <
1,
#104
0,
#105
b1001000 !
b1001000 1
b1001000 <
b1000 I
1,
#106
0,
#107
b1001 I
b1001001 !
b1001001 1
b1001001 <
1,
#108
0,
#109
b1010000 !
b1010000 1
b1010000 <
b1010 I
1,
#110
0,
#111
b1011 I
b1010001 !
b1010001 1
b1010001 <
1,
#112
0,
#113
b1010010 !
b1010010 1
b1010010 <
b1100 I
1,
#114
0,
#115
b1101 I
b1010011 !
b1010011 1
b1010011 <
1,
#116
0,
#117
b1010100 !
b1010100 1
b1010100 <
b1110 I
1,
#118
0,
#119
b1111 I
b1010101 !
b1010101 1
b1010101 <
1,
#120
0,
#121
b1010110 !
b1010110 1
b1010110 <
b10000 I
1,
#122
0,
#123
b10001 I
b1010111 !
b1010111 1
b1010111 <
1,
#124
0,
#125
b1011000 !
b1011000 1
b1011000 <
b10010 I
1,
#126
0,
#127
b10011 I
b1011001 !
b1011001 1
b1011001 <
1,
#128
0,
#129
b1 $
b1 2
b1 ;
b0 !
b0 1
b0 <
b10100 I
1,
#130
0,
#131
b10101 I
b1 !
b1 1
b1 <
1,
#132
0,
#133
b10 !
b10 1
b10 <
b10110 I
1,
#134
0,
#135
b10111 I
b11 !
b11 1
b11 <
1,
#136
0,
#137
b100 !
b100 1
b100 <
b11000 I
1,
#138
0,
#139
b11001 I
b101 !
b101 1
b101 <
1,
#140
0,
#141
b110 !
b110 1
b110 <
b11010 I
1,
#142
0,
#143
b11011 I
b111 !
b111 1
b111 <
1,
#144
0,
#145
b1000 !
b1000 1
b1000 <
b11100 I
1,
#146
0,
#147
b11101 I
b1001 !
b1001 1
b1001 <
1,
#148
0,
#149
b10000 !
b10000 1
b10000 <
b11110 I
1,
#150
0,
#151
b11111 I
b10001 !
b10001 1
b10001 <
1,
#152
0,
#153
b1 (
b1 6
b1 A
b1 *
b1 8
b1 ?
b10010 !
b10010 1
b10010 <
b0 I
1,
#154
0,
#155
b1 I
b10011 !
b10011 1
b10011 <
1,
#156
0,
#157
b10100 !
b10100 1
b10100 <
b10 I
1,
#158
0,
#159
b11 I
b10101 !
b10101 1
b10101 <
1,
#160
0,
#161
b10 (
b10 6
b10 A
1E
b10 *
b10 8
b10 ?
b10110 !
b10110 1
b10110 <
b0 I
1,
#162
0,
#163
b1 I
b10111 !
b10111 1
b10111 <
1,
#164
0,
#165
b11000 !
b11000 1
b11000 <
b10 I
1,
#166
0,
#167
b11 I
b11001 !
b11001 1
b11001 <
1,
#168
0,
#169
b0 '
b0 5
b0 B
0E
b0 )
b0 7
b0 @
b100000 !
b100000 1
b100000 <
b0 I
1,
#170
0,
#171
b1 I
b100001 !
b100001 1
b100001 <
1,
#172
0,
#173
b100010 !
b100010 1
b100010 <
b10 I
1,
#174
0,
#175
b11 I
b100011 !
b100011 1
b100011 <
1,
#176
0,
#177
b100100 !
b100100 1
b100100 <
b100 I
1,
#178
0,
#179
b101 I
b100101 !
b100101 1
b100101 <
1,
#180
0,
#181
b100110 !
b100110 1
b100110 <
b110 I
1,
#182
0,
#183
b111 I
b100111 !
b100111 1
b100111 <
1,
#184
0,
#185
b101000 !
b101000 1
b101000 <
b1000 I
1,
#186
0,
#187
b1001 I
b101001 !
b101001 1
b101001 <
1,
#188
0,
#189
b110000 !
b110000 1
b110000 <
b1010 I
1,
#190
0,
#191
b1011 I
b110001 !
b110001 1
b110001 <
1,
#192
0,
#193
b110010 !
b110010 1
b110010 <
b1100 I
1,
#194
0,
#195
b1101 I
b110011 !
b110011 1
b110011 <
1,
#196
0,
#197
b110100 !
b110100 1
b110100 <
b1110 I
1,
#198
0,
#199
b1111 I
b110101 !
b110101 1
b110101 <
1,
#200
0,
#201
b1 '
b1 5
b1 B
b1 )
b1 7
b1 @
b110110 !
b110110 1
b110110 <
b0 I
1,
#202
0,
#203
b1 I
b110111 !
b110111 1
b110111 <
1,
#204
0,
#205
b111000 !
b111000 1
b111000 <
b10 I
1,
#206
0,
#207
b11 I
b111001 !
b111001 1
b111001 <
1,
#208
0,
#209
b10 '
b10 5
b10 B
1G
b10 )
b10 7
b10 @
b1000000 !
b1000000 1
b1000000 <
b0 I
1,
#210
0,
#211
b1 I
b1000001 !
b1000001 1
b1000001 <
1,
#212
0,
#213
b1000010 !
b1000010 1
b1000010 <
b10 I
1,
#214
0,
#215
b11 I
b1000011 !
b1000011 1
b1000011 <
1,
#216
0,
#217
b0 &
b0 4
b0 C
0G
b0 +
b0 9
b0 >
b1000100 !
b1000100 1
b1000100 <
b0 I
1,
#218
0,
#219
b1 I
b1000101 !
b1000101 1
b1000101 <
1,
#220
0,
#221
b1000110 !
b1000110 1
b1000110 <
b10 I
1,
#222
0,
#223
b11 I
b1000111 !
b1000111 1
b1000111 <
1,
#224
0,
#225
b1001000 !
b1001000 1
b1001000 <
b100 I
1,
#226
0,
#227
b101 I
b1001001 !
b1001001 1
b1001001 <
1,
#228
0,
#229
b1010000 !
b1010000 1
b1010000 <
b110 I
1,
#230
0,
#231
b111 I
b1010001 !
b1010001 1
b1010001 <
1,
#232
0,
#233
b1010010 !
b1010010 1
b1010010 <
b1000 I
1,
#234
0,
#235
b1001 I
b1010011 !
b1010011 1
b1010011 <
1,
#236
0,
#237
b1010100 !
b1010100 1
b1010100 <
b1010 I
1,
#238
0,
#239
b1011 I
b1010101 !
b1010101 1
b1010101 <
1,
#240
0,
#241
b1010110 !
b1010110 1
b1010110 <
b1100 I
1,
#242
0,
#243
b1101 I
b1010111 !
b1010111 1
b1010111 <
1,
#244
0,
#245
b1011000 !
b1011000 1
b1011000 <
b1110 I
1,
#246
0,
#247
b1111 I
b1011001 !
b1011001 1
b1011001 <
1,
#248
0,
#249
b10 $
b10 2
b10 ;
b0 !
b0 1
b0 <
b10000 I
1,
#250
0,
#251
b10001 I
b1 !
b1 1
b1 <
1,
#252
0,
#253
b10 !
b10 1
b10 <
b10010 I
1,
#254
0,
#255
b10011 I
b11 !
b11 1
b11 <
1,
#256
0,
#257
b100 !
b100 1
b100 <
b10100 I
1,
#258
0,
#259
b10101 I
b101 !
b101 1
b101 <
1,
#260
0,
#261
b110 !
b110 1
b110 <
b10110 I
1,
#262
0,
#263
b10111 I
b111 !
b111 1
b111 <
1,
#264
0,
#265
b1000 !
b1000 1
b1000 <
b11000 I
1,
#266
0,
#267
b11001 I
b1001 !
b1001 1
b1001 <
1,
#268
0,
#269
b10000 !
b10000 1
b10000 <
b11010 I
1,
#270
0,
#271
b11011 I
b10001 !
b10001 1
b10001 <
1,
#272
0,
#273
b10010 !
b10010 1
b10010 <
b11100 I
1,
#274
0,
#275
b11101 I
b10011 !
b10011 1
b10011 <
1,
#276
0,
#277
b10100 !
b10100 1
b10100 <
b11110 I
1,
#278
0,
#279
b11111 I
b10101 !
b10101 1
b10101 <
1,
#280
0,
#281
b1 &
b1 4
b1 C
b1 +
b1 9
b1 >
b10110 !
b10110 1
b10110 <
b0 I
1,
#282
0,
#283
b1 I
b10111 !
b10111 1
b10111 <
1,
#284
0,
#285
b11000 !
b11000 1
b11000 <
b10 I
1,
#286
0,
#287
b11 I
b11001 !
b11001 1
b11001 <
1,
#288
0,
#289
b10 &
b10 4
b10 C
1D
b10 +
b10 9
b10 >
b100000 !
b100000 1
b100000 <
b0 I
1,
#290
0,
#291
b1 I
b100001 !
b100001 1
b100001 <
1,
#292
0,
#293
b100010 !
b100010 1
b100010 <
b10 I
1,
#294
0,
#295
b11 I
b100011 !
b100011 1
b100011 <
1,
#296
0,
#297
b0 (
b0 6
b0 A
0D
b0 *
b0 8
b0 ?
b100100 !
b100100 1
b100100 <
b0 I
1,
#298
0,
#299
b1 I
b100101 !
b100101 1
b100101 <
1,
#300
0,
#301
b100110 !
b100110 1
b100110 <
b10 I
1,
#302
0,
#303
b11 I
b100111 !
b100111 1
b100111 <
1,
#304
0,
#305
b101000 !
b101000 1
b101000 <
b100 I
1,
#306
0,
#307
b101 I
b101001 !
b101001 1
b101001 <
1,
#308
0,
#309
b110000 !
b110000 1
b110000 <
b110 I
1,
#310
0,
#311
b111 I
b110001 !
b110001 1
b110001 <
1,
#312
0,
#313
b110010 !
b110010 1
b110010 <
b1000 I
1,
#314
0,
#315
b1001 I
b110011 !
b110011 1
b110011 <
1,
#316
0,
#317
b110100 !
b110100 1
b110100 <
b1010 I
1,
#318
0,
#319
b1011 I
b110101 !
b110101 1
b110101 <
1,
#320
0,
#321
b110110 !
b110110 1
b110110 <
b1100 I
1,
#322
0,
#323
b1101 I
b110111 !
b110111 1
b110111 <
1,
#324
0,
#325
b111000 !
b111000 1
b111000 <
b1110 I
1,
#326
0,
#327
b1111 I
b111001 !
b111001 1
b111001 <
1,
#328
0,
#329
b1000000 !
b1000000 1
b1000000 <
b10000 I
1,
#330
0,
#331
b10001 I
b1000001 !
b1000001 1
b1000001 <
1,
#332
0,
#333
b1000010 !
b1000010 1
b1000010 <
b10010 I
1,
#334
0,
#335
b10011 I
b1000011 !
b1000011 1
b1000011 <
1,
#336
0,
#337
b1000100 !
b1000100 1
b1000100 <
b10100 I
1,
#338
0,
#339
b10101 I
b1000101 !
b1000101 1
b1000101 <
1,
#340
0,
#341
b1000110 !
b1000110 1
b1000110 <
b10110 I
1,
#342
0,
#343
b10111 I
b1000111 !
b1000111 1
b1000111 <
1,
#344
0,
#345
b1001000 !
b1001000 1
b1001000 <
b11000 I
1,
#346
0,
#347
b11001 I
b1001001 !
b1001001 1
b1001001 <
1,
#348
0,
#349
b1010000 !
b1010000 1
b1010000 <
b11010 I
1,
#350
0,
#351
b11011 I
b1010001 !
b1010001 1
b1010001 <
1,
#352
0,
#353
b1010010 !
b1010010 1
b1010010 <
b11100 I
1,
#354
0,
#355
b11101 I
b1010011 !
b1010011 1
b1010011 <
1,
#356
0,
#357
b1010100 !
b1010100 1
b1010100 <
b11110 I
1,
#358
0,
#359
b11111 I
b1010101 !
b1010101 1
b1010101 <
1,
#360
0,
#361
b1 (
b1 6
b1 A
b1 *
b1 8
b1 ?
b1010110 !
b1010110 1
b1010110 <
b0 I
1,
#362
0,
#363
b1 I
b1010111 !
b1010111 1
b1010111 <
1,
#364
0,
#365
b1011000 !
b1011000 1
b1011000 <
b10 I
1,
#366
0,
#367
b11 I
b1011001 !
b1011001 1
b1011001 <
1,
#368
0,
#369
b10 (
b10 6
b10 A
1E
b10 *
b10 8
b10 ?
b11 $
b11 2
b11 ;
b0 !
b0 1
b0 <
b0 I
1,
#370
0,
#371
b1 I
b1 !
b1 1
b1 <
1,
#372
0,
#373
b10 !
b10 1
b10 <
b10 I
1,
#374
0,
#375
b11 I
b11 !
b11 1
b11 <
1,
#376
0,
#377
b0 '
b0 5
b0 B
0E
b0 )
b0 7
b0 @
b100 !
b100 1
b100 <
b0 I
1,
#378
0,
#379
b1 I
b101 !
b101 1
b101 <
1,
#380
0,
#381
b110 !
b110 1
b110 <
b10 I
1,
#382
0,
#383
b11 I
b111 !
b111 1
b111 <
1,
#384
0,
#385
b1000 !
b1000 1
b1000 <
b100 I
1,
#386
0,
#387
b101 I
b1001 !
b1001 1
b1001 <
1,
#388
0,
#389
b10000 !
b10000 1
b10000 <
b110 I
1,
#390
0,
#391
b111 I
b10001 !
b10001 1
b10001 <
1,
